objectpath/__init__.py
objectpath/shell.py
objectpath/core/__init__.py
objectpath/core/interpreter.py
objectpath/core/parser.py
objectpath/utils/__init__.py
objectpath/utils/colorify.py
objectpath/utils/debugger.py
objectpath/utils/json_ext.py
objectpath/utils/timeutils.py
objectpath-0.6.dist-info/METADATA
objectpath-0.6.dist-info/RECORD
objectpath-0.6.dist-info/WHEEL
objectpath-0.6.dist-info/entry_points.txt
objectpath-0.6.dist-info/top_level.txt
objectpath-0.6.dist-info/zip-safe
