Metadata-Version: 2.1
Name: objectpath
Version: 0.6
Summary: The agile query language for semi-structured data. #JSON
Home-page: http://adriank.github.io/ObjectPath
Author: Adrian Kalbarczyk
Author-email: adrian.kalbarczyk@gmail.com
License: UNKNOWN
Keywords: query,tree,JSON,nested structures
Platform: UNKNOWN
Classifier: Development Status :: 6 - Mature
Classifier: Intended Audience :: Developers
Classifier: Intended Audience :: Science/Research
Classifier: License :: OSI Approved :: MIT License
Classifier: Programming Language :: Python
Classifier: Topic :: Software Development :: Libraries :: Python Modules
